setup.py
distributions_aleksa/Binomialdistribution.py
distributions_aleksa/Gaussiandistribution.py
distributions_aleksa/Generaldistribution.py
distributions_aleksa/__init__.py
distributions_aleksa.egg-info/PKG-INFO
distributions_aleksa.egg-info/SOURCES.txt
distributions_aleksa.egg-info/dependency_links.txt
distributions_aleksa.egg-info/not-zip-safe
distributions_aleksa.egg-info/top_level.txt