Metadata-Version: 1.0
Name: distributions-aleksa
Version: 0.2
Summary: Gaussian and Binomial distributions
Home-page: UNKNOWN
Author: UNKNOWN
Author-email: mihajlovic.aleksa@gmail.com
License: UNKNOWN
Platform: UNKNOWN
